pyptv/__init__.py
pyptv/__main__.py
pyptv/__version__.py
pyptv/calibration_gui.py
pyptv/cli.py
pyptv/code_editor.py
pyptv/detection_gui.py
pyptv/directory_editor.py
pyptv/draw_3d_target.py
pyptv/experiment.py
pyptv/file_editor_demo.py
pyptv/image_inspector.py
pyptv/imageplot.py
pyptv/imread_chaco.py
pyptv/legacy_parameters.py
pyptv/mask_gui.py
pyptv/optimize_calibration.ipynb
pyptv/parameter_gui.py
pyptv/parameter_manager.py
pyptv/parameter_util.py
pyptv/prepare_static_background.py
pyptv/ptv.py
pyptv/pyptv_batch.py
pyptv/pyptv_batch_parallel.py
pyptv/pyptv_batch_plugins.py
pyptv/pyptv_gui.py
pyptv/quiver_demo.py
pyptv/quiverplot.py
pyptv/scatter_inspector2.py
pyptv/text_box_overlay.py
pyptv-0.4.0.dist-info/licenses/LICENSE.txt
pyptv-0.4.0.dist-info/METADATA
pyptv-0.4.0.dist-info/WHEEL
pyptv-0.4.0.dist-info/entry_points.txt
pyptv-0.4.0.dist-info/top_level.txt
pyptv-0.4.0.dist-info/RECORD
