Metadata-Version: 2.4
Name: pyptv
Version: 0.4.0
Summary: Python GUI for the OpenPTV library `liboptv`
Author-email: Alex Liberzon <alex.liberzon@gmail.com>
License: MIT
Project-URL: Homepage, https://github.com/alexlib/pyptv
Project-URL: Documentation, https://openptv-python.readthedocs.io
Project-URL: Repository, https://github.com/alexlib/pyptv.git
Project-URL: Issues, https://github.com/alexlib/pyptv/issues
Project-URL: OpenPTV, http://www.openptv.net
Classifier: Development Status :: 4 - Beta
Classifier: Programming Language :: Python :: 3
Classifier: Programming Language :: Python :: 3.10
Classifier: Programming Language :: Python :: 3.11
Classifier: License :: OSI Approved :: MIT License
Classifier: Operating System :: OS Independent
Classifier: Topic :: Scientific/Engineering :: Physics
Classifier: Topic :: Scientific/Engineering :: Visualization
Requires-Python: >=3.10
License-File: LICENSE.txt
Requires-Dist: numpy==1.26.4
Requires-Dist: optv>=0.3.0
Requires-Dist: traits>=6.4.0
Requires-Dist: traitsui>=7.4.0
Requires-Dist: enable>=5.3.0
Requires-Dist: chaco>=5.1.0
Requires-Dist: PySide6>=6.0.0
Requires-Dist: scikit-image>=0.20.0
Requires-Dist: scipy>=1.10.0
Requires-Dist: pandas>=2.0.0
Requires-Dist: matplotlib>=3.7.0
Requires-Dist: tables>=3.8.0
Requires-Dist: tqdm>=4.65.0
Requires-Dist: imagecodecs>=2023.1.23
Requires-Dist: flowtracks>=0.3.0
Requires-Dist: Pygments>=2.15.0
Requires-Dist: pyparsing>=3.0.0
Requires-Dist: pytest>=8.4.1
Dynamic: license-file
